{
  "project": "hims",
  "displayName": "HIMS Pilot Recert",
  "cards": [
    {
      "id": "hims__slice1-pilot-detail",
      "title": "Slice 1 — Pilot detail page (intake, real DB)",
      "column": "done",
      "phase": "Merged to main (PR #5, squash); post-merge CI green",
      "nextAction": "Slice 2 — progress pane (plan just-in-time)",
      "blockedOn": null,
      "branch": null,
      "model": "Opus build / Fable merge-gate",
      "lastTouched": "2026-06-12",
      "links": {
        "pr": "https://github.com/argent-gnome/hims-pilot-recert/pull/5"
      }
    },
    {
      "id": "hims__slice2-progress-pane",
      "title": "Slice 2 — Progress pane",
      "column": "done",
      "phase": "Merged to main (PR #6, squash c4cb3e2); post-merge CI green",
      "nextAction": "Slice 3 (state-by-state event capture) or the auth/org-context slice",
      "blockedOn": null,
      "branch": "slice-2-progress-pane",
      "model": "Opus build / Fable merge-gate",
      "lastTouched": "2026-06-13",
      "links": {
        "spec": "docs/superpowers/specs/2026-06-12-slice2-progress-pane.md",
        "plan": "docs/superpowers/plans/2026-06-12-slice2-progress-pane.md",
        "pr": "https://github.com/argent-gnome/hims-pilot-recert/pull/6"
      }
    },
    {
      "id": "hims__auth-org-context",
      "links": {},
      "title": "Auth/session + per-org access hardening",
      "column": "backlog",
      "phase": "Deferred from Slice 1 (C1). Per-org tenancy/access hardening for the read + write paths — MUST close before go-live (pre-launch: no users, test data only). Specifics in the private repo (ADR 0001).",
      "nextAction": "Build the auth/session slice; bind per-org access for the read + write paths (see private ADR 0001).",
      "model": "Opus",
      "blockedOn": "Needs the auth/session slice",
      "lastTouched": "2026-06-12"
    },
    {
      "id": "hims__audit-record-immutability",
      "links": {},
      "title": "Audit-record immutability hardening",
      "column": "backlog",
      "phase": "Slice-0 audit (medium). Audit-record immutability follow-up — close before go-live. Specifics in the private repo.",
      "nextAction": "Harden audit-record immutability (see the private audit doc / ADR 0001).",
      "model": "Opus",
      "lastTouched": "2026-06-12"
    },
    {
      "id": "hims__rules-version-pinning",
      "links": {},
      "title": "Pin rule evaluation to the case's stored rules version",
      "column": "backlog",
      "phase": "Merge-gate NIT (B8): evaluation uses the latest rules version rather than the case's pinned version — identical today; matters after a rules-set change.",
      "nextAction": "Pin evaluation to the case's stored rules version.",
      "model": "Opus",
      "lastTouched": "2026-06-12"
    },
    {
      "id": "hims__slice3-event-capture",
      "links": {
        "spec": "docs/superpowers/specs/2026-06-15-slice3-contact-hims-ame.md",
        "plan": "docs/superpowers/plans/2026-06-15-slice3-contact-hims-ame.md",
        "pr": "https://github.com/argent-gnome/hims-pilot-recert/pull/7"
      },
      "title": "Slice 3 — State-by-state event capture",
      "column": "done",
      "phase": "Merged to main (PR #7, squash f8effee); first state-transition slice; CI billing-blocked (infra) → merged w/ comprehensive local + live verification per user auth; post-merge re-verified locally",
      "nextAction": "Slice 3b (next-state judgment) and/or the auth/org-context slice",
      "model": "all-Opus (Fable suspended)",
      "lastTouched": "2026-06-15",
      "branch": "slice-3-contact-hims-ame"
    },
    {
      "id": "hims__slice3b-judgment",
      "links": {
        "spec": "docs/superpowers/specs/2026-06-15-slice3b-nature-of-diagnosis.md",
        "plan": "docs/superpowers/plans/2026-06-15-slice3b-nature-of-diagnosis.md",
        "pr": "https://github.com/argent-gnome/hims-pilot-recert/pull/8"
      },
      "title": "Slice 3b — next-state judgment capture",
      "column": "done",
      "phase": "Merged to main (PR #8, squash 9d9064d); v0.11.0 flow (plan-check + merge-gate panel + health-sweep); CI billing-blocked → merged w/ local+live verification per user auth",
      "nextAction": "Slice 3c (under-3mo-wait→judgment entry) / on-med-3-months / auth slice",
      "model": "all-Opus (Fable suspended)",
      "lastTouched": "2026-06-15",
      "branch": "slice-3b-nature-of-diagnosis"
    },
    {
      "id": "hims__slice3c-wait-judgment",
      "links": {
        "spec": "docs/superpowers/specs/2026-06-15-slice3c-wait-judgment.md",
        "plan": "docs/superpowers/plans/2026-06-15-slice3c-wait-judgment.md",
        "pr": "https://github.com/argent-gnome/hims-pilot-recert/pull/9"
      },
      "title": "Slice 3c — under-3mo-wait → judgment entry",
      "column": "done",
      "phase": "Merged to main (PR #9, squash e00b7a7); cleanest run (plan-check PROCEED, 2 reviews clean, merge-gate GO); CI billing-blocked → merged w/ local+live verification",
      "nextAction": "Discontinue branch / on-med-3-months / auth slice / sdlc-auditor pass",
      "model": "all-Opus (profile opus)",
      "lastTouched": "2026-06-15",
      "branch": "slice-3c-wait-judgment"
    },
    {
      "id": "hims__slice3d-discontinue",
      "links": {
        "spec": "docs/superpowers/specs/2026-06-15-slice3d-discontinue.md",
        "plan": "docs/superpowers/plans/2026-06-15-slice3d-discontinue.md"
      },
      "title": "Slice 3d — elect-to-discontinue → block-60-deferred",
      "column": "verify",
      "phase": "Build complete (gates green, plan-check should-fix [clock-flip test] folded); two independent Opus reviews running",
      "nextAction": "Reviews → merge-gate panel → CI",
      "model": "all-Opus (profile opus)",
      "lastTouched": "2026-06-15",
      "branch": "slice-3d-discontinue"
    },
    {
      "id": "slice-3d",
      "links": {
        "pr": "https://github.com/argent-gnome/hims-pilot-recert/pull/10"
      },
      "column": "done",
      "phase": "Merged (PR #10 / b7303f0); post-merge main re-verified green",
      "nextAction": "Next slice: intake discontinue edge / on-med-3-months / auth-org-context slice; sdlc-auditor pass over 7+ retros; top up Actions budget",
      "lastTouched": "2026-06-15"
    },
    {
      "id": "slice-3e",
      "links": {
        "spec": "docs/superpowers/specs/2026-06-15-slice3e-regular-issuance.md",
        "pr": "https://github.com/argent-gnome/hims-pilot-recert/pull/11"
      },
      "title": "Off-meds terminus: block-60-deferred → regular-issuance-eligible",
      "column": "done",
      "phase": "Merged (PR #11 / 0e89944); post-merge main re-verified green; off-meds Path-I arc COMPLETE",
      "nextAction": "Next: on-meds arc (AMCD package states) / intake discontinue edge / auth-org-context slice; sdlc-auditor pass over 8+ retros; top up Actions budget",
      "model": "all-Opus (Fable suspended)",
      "lastTouched": "2026-06-15",
      "branch": "slice-3e-regular-issuance"
    },
    {
      "id": "slice-3f",
      "links": {
        "spec": "docs/superpowers/specs/2026-06-15-slice3f-intake-discontinue.md",
        "pr": "https://github.com/argent-gnome/hims-pilot-recert/pull/12"
      },
      "title": "Intake discontinue edge: on-antidepressant → block-60-deferred",
      "column": "done",
      "phase": "Merged (PR #12 / 8025edc); post-merge main re-verified green; off-meds Path-I arc reachable from the exam",
      "nextAction": "Next: continue-path entry fork (conditionally_acceptable) / AMCD package arc / auth-org-context slice; sdlc-auditor over 9+ retros; top up Actions budget",
      "model": "all-Opus (Fable suspended)",
      "lastTouched": "2026-06-16",
      "branch": "slice-3f-intake-discontinue"
    },
    {
      "id": "hims__slice-1",
      "title": "Slice 1 — first build on fixed foundation",
      "column": "done",
      "phase": "merged",
      "nextAction": "-",
      "blockedOn": null,
      "branch": "slice-1",
      "model": "Opus build / Fable merge-gate",
      "lastTouched": "2026-06-11",
      "links": {}
    },
    {
      "id": "slice-3g",
      "links": {
        "spec": "docs/superpowers/specs/2026-06-16-slice3g-continue-acceptability.md",
        "pr": "https://github.com/argent-gnome/hims-pilot-recert/pull/14"
      },
      "title": "Continue/acceptability fork: on-antidepressant → contact-hims-ame / not-acceptable (completes Path I)",
      "column": "done",
      "phase": "Merged (PR #14 / 480a7d5); post-merge main re-verified green; DECISION PATH I COMPLETE — front door open (intake→contact)",
      "nextAction": "Next: AMCD package arc (Path II endgame) / the auth-org-context slice; sdlc-auditor over 10+ retros; top up Actions budget",
      "model": "all-Opus (Fable suspended)",
      "lastTouched": "2026-06-16",
      "branch": "slice-3g-continue-acceptability"
    },
    {
      "id": "slice-4a",
      "links": {
        "spec": "docs/superpowers/specs/2026-06-16-slice4a-collecting-materials.md",
        "pr": "https://github.com/argent-gnome/hims-pilot-recert/pull/15"
      },
      "title": "AMCD arc 1: collecting-materials → hims-ame-review-package (package-complete attestation)",
      "column": "done",
      "phase": "Merged (PR #15 / 52421a4); post-merge main re-verified green; AMCD arc started (collecting → HIMS AME review); demo script updated",
      "nextAction": "Next AMCD: hims_ame_review_package→awaiting_faa_decision (submit-to-AMCD, 14-day clock) / the real report-requirements / auth slice",
      "model": "all-Opus (Fable suspended)",
      "lastTouched": "2026-06-16",
      "branch": "slice-4a-collecting-materials"
    },
    {
      "id": "slice-4b",
      "links": {
        "pr": "https://github.com/argent-gnome/hims-pilot-recert/pull/16"
      },
      "title": "AMCD arc 2: hims-ame-review-package → awaiting-faa-decision (submit to AMCD; 14-day clock)",
      "column": "done",
      "phase": "Merged (PR #16 / d976c9e); post-merge main re-verified green; submit-to-AMCD done, 14-day clock LIT; demo script updated",
      "nextAction": "Slice 4c — the FAA decision (awaiting_faa_decision→faa_issues_si/denied + denied re-entry) = AMCD arc COMPLETE; then run deferred 7½ + sdlc-auditor",
      "model": "all-Opus (Fable suspended)",
      "lastTouched": "2026-06-16",
      "branch": "slice-4b-submit-to-amcd"
    },
    {
      "id": "slice-4c",
      "links": {
        "spec": "docs/superpowers/specs/2026-06-17-slice4c-faa-decision.md",
        "pr": "https://github.com/argent-gnome/hims-pilot-recert/pull/17"
      },
      "title": "AMCD arc 3: FAA decision + re-entry (completes the journey)",
      "column": "done",
      "phase": "Merged (PR #17 / b18c2ec); post-merge main re-verified green; AMCD arc COMPLETE — full pilot journey end-to-end (intake → FAA SI/denied + re-entry)",
      "nextAction": "Arc-end: run deferred 7½ whole-arc health-sweep + sdlc-auditor (13+ retros); then auth/org-context slice OR depth (report-requirements / interim-reports)",
      "model": "all-Opus (Fable suspended)",
      "lastTouched": "2026-06-17",
      "branch": "slice-4c-faa-decision"
    },
    {
      "id": "slice-5a",
      "links": {
        "spec": "docs/superpowers/specs/2026-06-17-slice5a-auth-foundation.md",
        "pr": "https://github.com/argent-gnome/hims-pilot-recert/pull/18"
      },
      "title": "Auth foundation — login/session/route-protection (Supabase Auth)",
      "column": "done",
      "phase": "Merged (PR #18 / 5848448); post-merge main green (web 111); auth wall live; secret-safety verified",
      "nextAction": "Slice 5b — org-scoped data + RLS + audit actor (withDb role+GUC seam; activate existing RLS scaffolding; MedVector org/membership; recordedBy/changedBy; requireUser in actions). Connect Supabase MCP before 5b.",
      "model": "all-Opus (Fable suspended)",
      "lastTouched": "2026-06-17",
      "branch": "slice-5a-auth-foundation"
    },
    {
      "id": "slice-5b",
      "links": {
        "spec": "docs/superpowers/specs/2026-06-20-slice5b-org-rls.md",
        "pr": "https://github.com/argent-gnome/hims-pilot-recert/pull/19"
      },
      "title": "Org-scoped data + RLS + audit actor (go-live epic 2/3)",
      "column": "done",
      "phase": "Merged (PR #19 / a0d16f4); post-merge main green (db 38/web 115); RLS isolation ENFORCED, ADR-0001 superuser bypass retired, audit actor live",
      "nextAction": "5c (prod hard-gate + hosted Supabase/Vercel deploy → Dr. Stokes live URL; real APP_DB_PASSWORD; connect Supabase MCP) OR small 5b-cleanup (5a auth-backlog + conn pooling)",
      "model": "all-Opus (Fable suspended)",
      "lastTouched": "2026-06-21",
      "branch": "slice-5b-org-rls",
      "blockedOn": null
    },
    {
      "id": "slice-5c",
      "links": {
        "spec": "docs/superpowers/specs/2026-06-21-slice5c-deploy.md",
        "pr": "https://github.com/argent-gnome/hims-pilot-recert/pull/20"
      },
      "title": "Production hard-gate + hosted deploy (go-live epic 3/3)",
      "column": "live",
      "phase": "Part A merge-gate GO + folds in; PR #20 open (web 125, build green). Awaiting merge auth → then Part B deploy ops",
      "nextAction": "User merge auth (Part A) → ⛔ create Supabase → migrate/rls/seed → ⛔ Vercel deploy → smoke-test",
      "branch": "slice-5c-deploy",
      "model": "all-Opus (Fable suspended)",
      "lastTouched": "2026-06-21"
    }
  ]
}
